icvision/__init__.py
icvision/api.py
icvision/cli.py
icvision/cli_formatter.py
icvision/compat.py
icvision/config.py
icvision/core.py
icvision/eeglab.py
icvision/plotting.py
icvision/reports.py
icvision/utils.py
autocleaneeg_icvision-0.2.1.dist-info/METADATA
autocleaneeg_icvision-0.2.1.dist-info/WHEEL
autocleaneeg_icvision-0.2.1.dist-info/entry_points.txt
autocleaneeg_icvision-0.2.1.dist-info/licenses/LICENSE
autocleaneeg_icvision-0.2.1.dist-info/RECORD
