Metadata-Version: 2.4
Name: autocleaneeg-icvision
Version: 0.2.1
Summary: Automated ICA component classification using OpenAI Vision API for EEG data
Project-URL: Homepage, https://github.com/cincibrainlab/ICVision
Project-URL: Bug Reports, https://github.com/cincibrainlab/ICVision/issues
Project-URL: Source, https://github.com/cincibrainlab/ICVision
Project-URL: Documentation, https://cincibrainlab.github.io/ICVision/
Author-email: Gavin Gammoh <gavin.gammoh@cchmc.org>
Maintainer-email: Gavin Gammoh <gavin.gammoh@cchmc.org>
License: MIT License
License-File: LICENSE
Keywords: artifact-detection,eeg,ica,mne,neuroscience,openai,vision
Classifier: Development Status :: 4 - Beta
Classifier: Intended Audience :: Science/Research
Classifier: License :: OSI Approved :: MIT License
Classifier: Operating System :: OS Independent
Classifier: Programming Language :: Python
Classifier: Programming Language :: Python :: 3
Classifier: Programming Language :: Python :: 3.8
Classifier: Programming Language :: Python :: 3.9
Classifier: Programming Language :: Python :: 3.10
Classifier: Programming Language :: Python :: 3.11
Classifier: Programming Language :: Python :: 3.12
Classifier: Topic :: Scientific/Engineering
Classifier: Topic :: Scientific/Engineering :: Medical Science Apps.
Classifier: Typing :: Typed
Requires-Python: >=3.9
Requires-Dist: eeglabio
Requires-Dist: matplotlib>=3.5.0
Requires-Dist: mne>=1.5.0
Requires-Dist: numpy>=1.21.0
Requires-Dist: openai>=1.0.0
Requires-Dist: pandas>=1.5.0
Requires-Dist: pathlib-mate>=1.0.0
Requires-Dist: pillow>=9.0.0
Requires-Dist: python-dotenv>=0.19.0
Requires-Dist: scikit-learn>=1.0.0
Requires-Dist: scipy>=1.9.0
Provides-Extra: dev
Requires-Dist: bandit[toml]>=1.7.5; extra == 'dev'
Requires-Dist: black>=23.0.0; extra == 'dev'
Requires-Dist: build>=0.10.0; extra == 'dev'
Requires-Dist: flake8>=6.0.0; extra == 'dev'
Requires-Dist: isort>=5.12.0; extra == 'dev'
Requires-Dist: mypy>=1.0.0; extra == 'dev'
Requires-Dist: pre-commit>=3.0.0; extra == 'dev'
Requires-Dist: pydocstyle>=6.3.0; extra == 'dev'
Requires-Dist: pytest-cov>=4.0.0; extra == 'dev'
Requires-Dist: pytest-mock>=3.5.0; extra == 'dev'
Requires-Dist: pytest>=7.0.0; extra == 'dev'
Requires-Dist: tox>=4.0.0; extra == 'dev'
Requires-Dist: twine>=4.0.0; extra == 'dev'
Provides-Extra: docs
Requires-Dist: myst-parser>=1.0.0; extra == 'docs'
Requires-Dist: numpydoc>=1.5.0; extra == 'docs'
Requires-Dist: sphinx-rtd-theme>=1.2.0; extra == 'docs'
Requires-Dist: sphinx>=5.0.0; extra == 'docs'
Provides-Extra: test
Requires-Dist: pytest-cov>=4.0.0; extra == 'test'
Requires-Dist: pytest-mock>=3.5.0; extra == 'test'
Requires-Dist: pytest>=7.0.0; extra == 'test'
